seshat/__init__.py
seshat/__main__.py
seshat/_story-hierarchical.json
seshat/_story.json
seshat/data_class/__init__.py
seshat/data_class/base.py
seshat/data_class/pandas.py
seshat/data_class/pyspark.py
seshat/evaluation/__init__.py
seshat/evaluation/base.py
seshat/evaluation/evaluator/__init__.py
seshat/evaluation/evaluator/base.py
seshat/evaluation/evaluator/general/__init__.py
seshat/evaluation/evaluator/general/classification.py
seshat/evaluation/evaluator/general/clustering.py
seshat/evaluation/evaluator/general/regression.py
seshat/evaluation/evaluator/recommendation/__init__.py
seshat/evaluation/evaluator/recommendation/diversity.py
seshat/evaluation/evaluator/recommendation/ranking.py
seshat/feature_view/__init__.py
seshat/feature_view/base.py
seshat/general/__init__.py
seshat/general/command/__init__.py
seshat/general/command/base.py
seshat/general/command/code_inspect.py
seshat/general/command/job_status.py
seshat/general/command/setup_project.py
seshat/general/command/submit_to_network.py
seshat/general/config.py
seshat/general/exceptions.py
seshat/general/lazy_config.py
seshat/general/models.py
seshat/general/template/README.md-tmpl
seshat/general/template/config.py-tmpl
seshat/general/template/env-templ
seshat/general/template/jobignore-tmpl
seshat/general/template/pyproject._toml-tmpl
seshat/general/template/recommender-jupyter.ipynb-tmpl
seshat/general/template/recommender.py-tmpl
seshat/general/transformer_story/__init__.py
seshat/general/transformer_story/base.py
seshat/general/transformer_story/challenges.py
seshat/profiler/__init__.py
seshat/profiler/base.py
seshat/profiler/decorator.py
seshat/profiler/format.py
seshat/source/__init__.py
seshat/source/api/__init__.py
seshat/source/api/base.py
seshat/source/api/scrape.py
seshat/source/base.py
seshat/source/database/__init__.py
seshat/source/database/base.py
seshat/source/exceptions.py
seshat/source/local/__init__.py
seshat/source/local/base.py
seshat/source/mixins.py
sdk_seshat_python-0.6.1.dist-info/LICENSE
sdk_seshat_python-0.6.1.dist-info/METADATA
sdk_seshat_python-0.6.1.dist-info/WHEEL
sdk_seshat_python-0.6.1.dist-info/RECORD
