Metadata-Version: 2.1
Name: sdk-seshat-python
Version: 0.6.1
Summary: Seshat python SDK is a library to help create ML data pipelines.
License: Commercial - see LICENSE.txt
Author: SeshatLabs
Author-email: info@seshatlabs.xyz
Requires-Python: >=3.11,<4.0
Classifier: License :: Other/Proprietary License
Classifier: Programming Language :: Python :: 3
Classifier: Programming Language :: Python :: 3.11
Requires-Dist: backoff (>=2.2.1,<3.0.0)
Requires-Dist: beautifulsoup4 (>=4.14.3,<5.0.0)
Requires-Dist: bokeh (>=3.6.0,<4.0.0)
Requires-Dist: boto3 (==1.40.51)
Requires-Dist: croniter (>=6.0.0,<7.0.0)
Requires-Dist: cryptography (==46.0.3)
Requires-Dist: dask[array,complete,dataframe,distributed] (>=2024.10.0,<2025.0.0)
Requires-Dist: google-cloud-aiplatform (>=1.120.0,<2.0.0)
Requires-Dist: langchain (==0.3.27)
Requires-Dist: langchain-aws (==0.2.35)
Requires-Dist: langchain-community (==0.3.31)
Requires-Dist: langchain-google-vertexai (>=2.1.2,<3.0.0)
Requires-Dist: langchain-openai (==0.3.35)
Requires-Dist: loguru (>=0.7.3,<0.8.0)
Requires-Dist: memory-profiler (>=0.61.0,<0.62.0)
Requires-Dist: openai (==2.15.0)
Requires-Dist: pandas (>=2.3.3,<3.0.0)
Requires-Dist: psycopg2-binary (==2.9.11)
Requires-Dist: pyarmor (>=9.2.3,<10.0.0)
Requires-Dist: pydantic (==2.12.5)
Requires-Dist: pyspark (>=3.5.1,<4.0.0)
Requires-Dist: python-logstash-async (>=4.0.2,<5.0.0)
Requires-Dist: requests (==2.32.5)
Requires-Dist: rich (==14.2.0)
Requires-Dist: scikit-learn (>=1.4.1.post1,<2.0.0)
Requires-Dist: setuptools (>=80.9.0,<81.0.0)
Requires-Dist: simplejson (>=3.20.2,<4.0.0)
Requires-Dist: sqlalchemy (>=2.0.45,<3.0.0)
Requires-Dist: toml (>=0.10.2,<0.11.0)
Requires-Dist: typer (>=0.19.2,<0.20.0)
